<?xml version="1.0" encoding="UTF-8" standalone="no"?>
<positions>
    <postion>
        <x>0</x>
        <y>0</y>
    </postion>
    <postion>
        <x>1</x>
        <y>0</y>
    </postion>
    <postion>
        <x>2</x>
        <y>0</y>
    </postion>
    <postion>
        <x>3</x>
        <y>0</y>
    </postion>
    <postion>
        <x>4</x>
        <y>0</y>
    </postion>
    <postion>
        <x>5</x>
        <y>0</y>
    </postion>
    <postion>
        <x>6</x>
        <y>0</y>
    </postion>
</positions>